models/ModelFactory.py
models/__init__.py
models/my_model.py
models/ratio.py
utils/__init__.py
utils/dataset.py
utils/loader.py
utils/metrics.py
utils/split.py
utils/styles.py
TimeToEvent-1.0.0.dist-info/LICENSE.txt
TimeToEvent-1.0.0.dist-info/METADATA
TimeToEvent-1.0.0.dist-info/WHEEL
TimeToEvent-1.0.0.dist-info/top_level.txt
TimeToEvent-1.0.0.dist-info/RECORD
